MANIFEST.in
README.md
setup.cfg
setup.py
autoguru/VERSION.txt
autoguru/__init__.py
autoguru/__main__.py
autoguru/autoguru.py
autoguru/model.py
autoguru.egg-info/PKG-INFO
autoguru.egg-info/SOURCES.txt
autoguru.egg-info/dependency_links.txt
autoguru.egg-info/entry_points.txt
autoguru.egg-info/requires.txt
autoguru.egg-info/top_level.txt
autoguru.egg-info/zip-safe
autoguru/discord/__init__.py
autoguru/discord/__main__.py
autoguru/discord/bot.py
autoguru/embeddings/__init__.py
autoguru/embeddings/use.py
autoguru/nearestneighbors/__init__.py
autoguru/nearestneighbors/hnsw.py
autoguru/simple/__init__.py
autoguru/simple/__main__.py
autoguru/simple/model.py