Metadata-Version: 2.1
Name: autoguru
Version: 0.0.1
Summary: Question Answering for FAQs with Natural Language Processing
Home-page: https://github.com/robrua/autoguru
Author: Rob Rua
Author-email: robertrua@gmail.com
License: MIT
Download-URL: https://github.com/robrua/autoguru/archive/v0.0.1.tar.gz
Platform: UNKNOWN
Classifier: Development Status :: 3 - Alpha
Classifier: License :: OSI Approved :: MIT License
Classifier: Intended Audience :: Developers
Classifier: Intended Audience :: Customer Service
Classifier: Natural Language :: English
Classifier: Operating System :: OS Independent
Classifier: Programming Language :: Python :: 3
Classifier: Programming Language :: Python :: 3 :: Only
Classifier: Programming Language :: Python :: 3.5
Classifier: Programming Language :: Python :: 3.6
Classifier: Programming Language :: Python :: 3.7
Classifier: Programming Language :: Python :: 3.8
Classifier: Programming Language :: Python :: 3.9
Classifier: Topic :: Communications :: Chat
Classifier: Topic :: Documentation
Classifier: Typing :: Typed
Requires-Python: >=3.5
